pytest_timeout.py
pytest_timeout-2.2.0.dist-info/LICENSE
pytest_timeout-2.2.0.dist-info/METADATA
pytest_timeout-2.2.0.dist-info/WHEEL
pytest_timeout-2.2.0.dist-info/entry_points.txt
pytest_timeout-2.2.0.dist-info/top_level.txt
pytest_timeout-2.2.0.dist-info/RECORD
